{
  "debug_mode": true,
  "filter_out_non_fixations": false,
  "max_sequence_length": -1,
  "bg_image": {
    "show": false,
    "filename": "cookie_theft_aoi.jpeg"
  },
  "proportions": {
    "active": true,
    "origin": "upper",
    "width": 1280,
    "height": 1024
  },
  "paths": {
    "source": {
      "data_folder": "dataset",
      "modality": "sequences",
      "data_source": "eye_tracking",
      "representation": "random_sampled_gaze_fixations_400",
      "data_dimension": "augmented"
    },
    "destination": {
      "data_folder": "preprocessed",
      "modality": "images",
      "data_source": "eye_tracking",
      "representation": "heatmaps_random_sampled_gaze_fixations_400",
      "data_dimension": "augmented"
    }
  }
}